airtable_scraper/__init__.py
airtable_scraper/_logger_config.py
airtable_scraper/_models.py
airtable_scraper/airtable_scraper.py
airtable_scraper/table_utils.py
airtable_scraper/typing.py
airtable_scraper-0.0.3.dist-info/LICENSE
airtable_scraper-0.0.3.dist-info/METADATA
airtable_scraper-0.0.3.dist-info/WHEEL
airtable_scraper-0.0.3.dist-info/top_level.txt
airtable_scraper-0.0.3.dist-info/RECORD
