Metadata-Version: 2.1
Name: airtable_scraper
Version: 0.0.3
Summary: Public airtable web scraper tool
Author-email: Kang Chen <kangchen.work@gmail.com>
License: MIT License
Project-URL: Homepage, https://github.com/kchenTTP/airtable-scraper
Project-URL: Issues, https://github.com/kchenTTP/airtable-scraper/issues
Keywords: airtable,scraper,scraping,web scraper
Classifier: Programming Language :: Python :: 3
Classifier: License :: OSI Approved :: MIT License
Classifier: Operating System :: OS Independent
Requires-Python: >=3.8
License-File: LICENSE
Requires-Dist: pandas
Requires-Dist: pydantic
Requires-Dist: pytz
Requires-Dist: requests
